setup.py
pinry/__init__.py
pinry/test_runner.py
pinry/urls.py
pinry.egg-info/PKG-INFO
pinry.egg-info/SOURCES.txt
pinry.egg-info/dependency_links.txt
pinry.egg-info/requires.txt
pinry.egg-info/top_level.txt
pinry/core/__init__.py
pinry/core/api.py
pinry/core/context_processors.py
pinry/core/forms.py
pinry/core/models.py
pinry/core/urls.py
pinry/core/utils.py
pinry/core/views.py
pinry/core/management/__init__.py
pinry/core/management/commands/__init__.py
pinry/core/management/commands/flickr.py
pinry/core/migrations/0001_initial.py
pinry/core/migrations/__init__.py
pinry/core/templatetags/__init__.py
pinry/core/templatetags/bootstrap_field.py
pinry/settings/__init__.py
pinry/settings/development.py
pinry/settings/production.py
pinry/settings/test.py
pinry/users/__init__.py
pinry/users/forms.py
pinry/users/middleware.py
pinry/users/models.py
pinry/users/tests.py
pinry/users/urls.py
pinry/users/views.py
pinry/users/auth/__init__.py
pinry/users/auth/backends.py