Metadata-Version: 1.1
Name: pinry
Version: 1.1.0
Summary: A tiling image board system for people who want to save, tag, and share images, videos and webpages.
Home-page: http://packages.python.org/pinry
Author: Pinry contributors
Author-email: devs@getpinry.com
License: AGPL-3+
Keywords: web pictures kittens
Platform: UNKNOWN
Classifier: Development Status :: 4 - Beta
Classifier: Framework :: Django
Classifier: Environment :: Web Environment
Classifier: License :: OSI Approved :: GNU Affero General Public License v3 or later (AGPLv3+)
